seeq/sdk/__init__.py
seeq/sdk/api_client.py
seeq/sdk/configuration.py
seeq/sdk/rest.py
seeq/sdk/api/__init__.py
seeq/sdk/api/access_keys_api.py
seeq/sdk/api/add_ons_api.py
seeq/sdk/api/agents_api.py
seeq/sdk/api/annotations_api.py
seeq/sdk/api/assets_api.py
seeq/sdk/api/audit_api.py
seeq/sdk/api/auth_api.py
seeq/sdk/api/cache_api.py
seeq/sdk/api/condition_monitors_api.py
seeq/sdk/api/conditions_api.py
seeq/sdk/api/content_api.py
seeq/sdk/api/context_api.py
seeq/sdk/api/datafiles_api.py
seeq/sdk/api/datasources_api.py
seeq/sdk/api/display_templates_api.py
seeq/sdk/api/displays_api.py
seeq/sdk/api/export_api.py
seeq/sdk/api/folders_api.py
seeq/sdk/api/formulas_api.py
seeq/sdk/api/graph_ql_api.py
seeq/sdk/api/hierarchies_api.py
seeq/sdk/api/items_api.py
seeq/sdk/api/jobs_api.py
seeq/sdk/api/logs_api.py
seeq/sdk/api/markdown_items_api.py
seeq/sdk/api/markdown_links_api.py
seeq/sdk/api/materialized_tables_api.py
seeq/sdk/api/metrics_api.py
seeq/sdk/api/models_api.py
seeq/sdk/api/monitors_api.py
seeq/sdk/api/networks_api.py
seeq/sdk/api/notification_configurations_api.py
seeq/sdk/api/notifier_api.py
seeq/sdk/api/plugins_api.py
seeq/sdk/api/projects_api.py
seeq/sdk/api/report_templates_api.py
seeq/sdk/api/reports_api.py
seeq/sdk/api/requests_api.py
seeq/sdk/api/scalars_api.py
seeq/sdk/api/scim_api.py
seeq/sdk/api/sharing_api.py
seeq/sdk/api/signal_monitors_api.py
seeq/sdk/api/signals_api.py
seeq/sdk/api/stored_tables_api.py
seeq/sdk/api/subscriptions_api.py
seeq/sdk/api/system_api.py
seeq/sdk/api/table_definitions_api.py
seeq/sdk/api/trees_api.py
seeq/sdk/api/usage_api.py
seeq/sdk/api/user_groups_api.py
seeq/sdk/api/users_api.py
seeq/sdk/api/workbooks_api.py
seeq/sdk/models/__init__.py
seeq/sdk/models/access_key_input_v1.py
seeq/sdk/models/access_key_output_list_v1.py
seeq/sdk/models/access_key_output_v1.py
seeq/sdk/models/ace_input_v1.py
seeq/sdk/models/ace_output_v1.py
seeq/sdk/models/acl_input_v1.py
seeq/sdk/models/acl_output_v1.py
seeq-66.91.2.20251230.dist-info/METADATA
seeq-66.91.2.20251230.dist-info/WHEEL
seeq-66.91.2.20251230.dist-info/top_level.txt
seeq-66.91.2.20251230.dist-info/RECORD
