Metadata-Version: 2.4
Name: seeq
Version: 66.91.2.20251230
Summary: The Seeq SDK for Python
Author-email: Seeq Corporation <support@seeq.com>
License: Seeq Python Library – License File
Project-URL: Homepage, https://www.seeq.com
Project-URL: Documentation, https://python-docs.seeq.com/
Project-URL: Changelog, https://python-docs.seeq.com/changelog.html
Classifier: Programming Language :: Python :: 2
Classifier: Programming Language :: Python :: 3
Classifier: License :: Other/Proprietary License
Classifier: Operating System :: OS Independent
Requires-Python: >=2.7
Requires-Dist: certifi>=14.05.14
Requires-Dist: six>=1.10
Requires-Dist: urllib3<3.0.0,>=1.15.1
Requires-Dist: requests>=2.21.0
Requires-Dist: cryptography>=3.2
